quart_assets/__init__.py
quart_assets/extension.py
quart_assets-0.1.2.dist-info/LICENSE
quart_assets-0.1.2.dist-info/METADATA
quart_assets-0.1.2.dist-info/WHEEL
quart_assets-0.1.2.dist-info/entry_points.txt
quart_assets-0.1.2.dist-info/RECORD
