Metadata-Version: 2.3
Name: quart-assets
Version: 0.1.2
Summary: Asset management for Quart apps
License: BSD-2-Clause
Author: Sasha Gerrand
Author-email: quart-assets@sgerrand.dev
Requires-Python: >=3.9
Classifier: Environment :: Web Environment
Classifier: Intended Audience :: Developers
Classifier: License :: OSI Approved :: BSD License
Classifier: Operating System :: OS Independent
Classifier: Programming Language :: Python :: 3
Classifier: Programming Language :: Python :: 3.9
Classifier: Programming Language :: Python :: 3.10
Classifier: Programming Language :: Python :: 3.11
Classifier: Programming Language :: Python :: 3.12
Classifier: Programming Language :: Python :: 3.13
Classifier: Topic :: Internet :: WWW/HTTP :: Dynamic Content
Classifier: Topic :: Software Development :: Libraries :: Python Modules
Requires-Dist: pyscss
Requires-Dist: pyyaml
Requires-Dist: quart (>=0.20.0,<0.21.0)
Requires-Dist: webassets (>=2.0)
Project-URL: Bug Tracker, https://github.com/sgerrand/quart-assets/issues
Project-URL: Documentation, https://quart-assets.readthedocs.io
Project-URL: Homepage, https://github.com/sgerrand/quart-assets
Project-URL: Repository, https://github.com/sgerrand/quart-assets
